certdumper/__init__.py
certdumper/certs.py
certdumper/cli.py
certdumper/conf.py
certdumper/exc.py
certdumper/types.py
certdumper/util.py
certdumper-0.1.0.dist-info/entry_points.txt
certdumper-0.1.0.dist-info/WHEEL
certdumper-0.1.0.dist-info/METADATA
certdumper-0.1.0.dist-info/RECORD
